{
  "project_info": {
    "project_number": "459908628307",
    "firebase_url": "https://colorful-intelligence.firebaseio.com",
    "project_id": "colorful-intelligence",
    "storage_bucket": "colorful-intelligence.appspot.com"
  },
  "client": [
    {
      "client_info": {
        "mobilesdk_app_id": "1:459908628307:android:2a8b0da582e1c9576aaba6",
        "android_client_info": {
          "package_name": "com.uren.motleybrain"
        }
      },
      "oauth_client": [
        {
          "client_id": "459908628307-kqi6a0p758lqla94rmeunqbeqv6u75kb.apps.googleusercontent.com",
          "client_type": 1,
          "android_info": {
            "package_name": "com.uren.motleybrain",
            "certificate_hash": "835135492279180c8c9d6517641665756f89cf21"
          }
        },
        {
          "client_id": "459908628307-ur0jefm4b1flt9qgcn37hb1ondjuf285.apps.googleusercontent.com",
          "client_type": 3
        }
      ],
      "api_key": [
        {
          "current_key": "AIzaSyBw-hLI39711ysCe52RuWs-UpPiPuLC1sM"
        }
      ],
      "services": {
        "appinvite_service": {
          "other_platform_oauth_client": [
            {
              "client_id": "459908628307-ur0jefm4b1flt9qgcn37hb1ondjuf285.apps.googleusercontent.com",
              "client_type": 3
            }
          ]
        }
      }
    }
  ],
  "configuration_version": "1"
}